domestobot/__init__.py
domestobot/__main__.py
domestobot/_app.py
domestobot/_config.py
domestobot/_core.py
domestobot/_steps.py
domestobot/py.typed
domestobot-0.1.3.dist-info/LICENSE
domestobot-0.1.3.dist-info/METADATA
domestobot-0.1.3.dist-info/WHEEL
domestobot-0.1.3.dist-info/entry_points.txt
domestobot-0.1.3.dist-info/RECORD
