Metadata-Version: 2.3
Name: domestobot
Version: 0.1.3
Summary: Your own trusty housekeeper: https://github.com/AliGhahraei/domestobot
License: GNU GENERAL PUBLIC LICENSE
Author: Ali Ghahraei Figueroa
Author-email: aligf94@gmail.com
Requires-Python: >=3.13.3,<4.0
Classifier: Programming Language :: Python :: 3
Classifier: License :: OSI Approved :: GNU General Public License v3 or later (GPLv3+)
Classifier: Operating System :: POSIX :: Linux
Classifier: Operating System :: MacOS
Classifier: Operating System :: Unix
Requires-Dist: pydantic (>=2.11.5,<3.0.0)
Requires-Dist: tomlkit (>=0.13.2,<0.14.0)
Requires-Dist: typer (>=0.16.0,<0.16.1)
Requires-Dist: xdg (>=6.0.0,<7.0.0)
Project-URL: Home, https://github.com/AliGhahraei/domestobot
